psdm2pp/__init__.py
psdm2pp/grid.py
psdm2pp-0.1.0.dist-info/LICENSE
psdm2pp-0.1.0.dist-info/METADATA
psdm2pp-0.1.0.dist-info/WHEEL
psdm2pp-0.1.0.dist-info/RECORD
