Metadata-Version: 2.1
Name: psdm2pp
Version: 0.1.0
Summary: 
Author: Thomas
Author-email: thomas.oberliessen@googlemail.com
Requires-Python: >3.11,<3.12
Classifier: Programming Language :: Python :: 3
Requires-Dist: pandapower (>=2.14.11,<3.0.0)
Requires-Dist: pypsdm (>=0.0.3,<0.0.4)
Requires-Dist: simbench (>=1.5.3,<2.0.0)
